rotation_random_forest/RotationRandomForest.py
rotation_random_forest/RotationTree.py
rotation_random_forest/__init__.py
rotation_random_forest-0.1.1.dist-info/WHEEL
rotation_random_forest-0.1.1.dist-info/METADATA
rotation_random_forest-0.1.1.dist-info/RECORD
